
#define ASM4 262144
#define ASM5 327680
#define V1_1 196653
#define V1_2 46
#define V1_3 47
#define V1_4 48
#define V1_5 49
#define V1_6 50
#define V1_7 51
#define V1_8 52
#define ACC_PUBLIC 1
#define ACC_PRIVATE 2
#define ACC_PROTECTED 4
#define ACC_STATIC 8
#define ACC_FINAL 16
#define ACC_SUPER 32
#define ACC_SYNCHRONIZED 32
#define ACC_VOLATILE 64
#define ACC_BRIDGE 64
#define ACC_VARARGS 128
#define ACC_TRANSIENT 128
#define ACC_NATIVE 256
#define ACC_INTERFACE 512
#define ACC_ABSTRACT 1024
#define ACC_STRICT 2048
#define ACC_SYNTHETIC 4096
#define ACC_ANNOTATION 8192
#define ACC_ENUM 16384
#define ACC_MANDATED 32768
#define ACC_DEPRECATED 131072
#define T_BOOLEAN 4
#define T_CHAR 5
#define T_FLOAT 6
#define T_DOUBLE 7
#define T_BYTE 8
#define T_SHORT 9
#define T_INT 10
#define T_LONG 11
#define H_GETFIELD 1
#define H_GETSTATIC 2
#define H_PUTFIELD 3
#define H_PUTSTATIC 4
#define H_INVOKEVIRTUAL 5
#define H_INVOKESTATIC 6
#define H_INVOKESPECIAL 7
#define H_NEWINVOKESPECIAL 8
#define H_INVOKEINTERFACE 9
#define F_NEW -1
#define F_FULL 0
#define F_APPEND 1
#define F_CHOP 2
#define F_SAME 3
#define F_SAME1 4
#define NOP 0
#define ACONST_NULL 1
#define ICONST_M1 2
#define ICONST_0 3
#define ICONST_1 4
#define ICONST_2 5
#define ICONST_3 6
#define ICONST_4 7
#define ICONST_5 8
#define LCONST_0 9
#define LCONST_1 10
#define FCONST_0 11
#define FCONST_1 12
#define FCONST_2 13
#define DCONST_0 14
#define DCONST_1 15
#define BIPUSH 16
#define SIPUSH 17
#define LDC 18
#define ILOAD 21
#define LLOAD 22
#define FLOAD 23
#define DLOAD 24
#define ALOAD 25
#define IALOAD 46
#define LALOAD 47
#define FALOAD 48
#define DALOAD 49
#define AALOAD 50
#define BALOAD 51
#define CALOAD 52
#define SALOAD 53
#define ISTORE 54
#define LSTORE 55
#define FSTORE 56
#define DSTORE 57
#define ASTORE 58
#define IASTORE 79
#define LASTORE 80
#define FASTORE 81
#define DASTORE 82
#define AASTORE 83
#define BASTORE 84
#define CASTORE 85
#define SASTORE 86
#define POP 87
#define POP2 88
#define DUP 89
#define DUP_X1 90
#define DUP_X2 91
#define DUP2 92
#define DUP2_X1 93
#define DUP2_X2 94
#define SWAP 95
#define IADD 96
#define LADD 97
#define FADD 98
#define DADD 99
#define ISUB 100
#define LSUB 101
#define FSUB 102
#define DSUB 103
#define IMUL 104
#define LMUL 105
#define FMUL 106
#define DMUL 107
#define IDIV 108
#define LDIV 109
#define FDIV 110
#define DDIV 111
#define IREM 112
#define LREM 113
#define FREM 114
#define DREM 115
#define INEG 116
#define LNEG 117
#define FNEG 118
#define DNEG 119
#define ISHL 120
#define LSHL 121
#define ISHR 122
#define LSHR 123
#define IUSHR 124
#define LUSHR 125
#define IAND 126
#define LAND 127
#define IOR 128
#define LOR 129
#define IXOR 130
#define LXOR 131
#define IINC 132
#define I2L 133
#define I2F 134
#define I2D 135
#define L2I 136
#define L2F 137
#define L2D 138
#define F2I 139
#define F2L 140
#define F2D 141
#define D2I 142
#define D2L 143
#define D2F 144
#define I2B 145
#define I2C 146
#define I2S 147
#define LCMP 148
#define FCMPL 149
#define FCMPG 150
#define DCMPL 151
#define DCMPG 152
#define IFEQ 153
#define IFNE 154
#define IFLT 155
#define IFGE 156
#define IFGT 157
#define IFLE 158
#define IF_ICMPEQ 159
#define IF_ICMPNE 160
#define IF_ICMPLT 161
#define IF_ICMPGE 162
#define IF_ICMPGT 163
#define IF_ICMPLE 164
#define IF_ACMPEQ 165
#define IF_ACMPNE 166
#define GOTO 167
#define JSR 168
#define RET 169
#define TABLESWITCH 170
#define LOOKUPSWITCH 171
#define IRETURN 172
#define LRETURN 173
#define FRETURN 174
#define DRETURN 175
#define ARETURN 176
#define RETURN 177
#define GETSTATIC 178
#define PUTSTATIC 179
#define GETFIELD 180
#define PUTFIELD 181
#define INVOKEVIRTUAL 182
#define INVOKESPECIAL 183
#define INVOKESTATIC 184
#define INVOKEINTERFACE 185
#define INVOKEDYNAMIC 186
#define NEW 187
#define NEWARRAY 188
#define ANEWARRAY 189
#define ARRAYLENGTH 190
#define ATHROW 191
#define CHECKCAST 192
#define INSTANCEOF 193
#define MONITORENTER 194
#define MONITOREXIT 195
#define MULTIANEWARRAY 197
#define IFNULL 198
#define IFNONNULL 199
